database_schema_ensurer/__init__.py
database_schema_ensurer/database_schema_ensurer.py
database_schema_ensurer-2.0.0.dist-info/METADATA
database_schema_ensurer-2.0.0.dist-info/WHEEL
database_schema_ensurer-2.0.0.dist-info/RECORD
